LICENSE
MANIFEST.in
README.md
setup.cfg
setup.py
limix_inference/__init__.py
limix_inference.egg-info/PKG-INFO
limix_inference.egg-info/SOURCES.txt
limix_inference.egg-info/dependency_links.txt
limix_inference.egg-info/not-zip-safe
limix_inference.egg-info/requires.txt
limix_inference.egg-info/top_level.txt
limix_inference/cov/__init__.py
limix_inference/cov/eye.py
limix_inference/cov/free.py
limix_inference/cov/given.py
limix_inference/cov/linear.py
limix_inference/cov/sum.py
limix_inference/cov/test/test_eye_cov.py
limix_inference/cov/test/test_free_cov.py
limix_inference/cov/test/test_given_cov.py
limix_inference/cov/test/test_linear_cov.py
limix_inference/cov/test/test_sum_cov.py
limix_inference/ep/__init__.py
limix_inference/ep/ep.py
limix_inference/ep/posterior.py
limix_inference/ep/site.py
limix_inference/ep/test/test_ep.py
limix_inference/example/__init__.py
limix_inference/ggp/__init__.py
limix_inference/ggp/expfam.py
limix_inference/ggp/test/test_expfamgp.py
limix_inference/glmm/__init__.py
limix_inference/glmm/glmm.py
limix_inference/glmm/test/test_glmm.py
limix_inference/gp/__init__.py
limix_inference/gp/gp.py
limix_inference/gp/test/test_gp.py
limix_inference/lik/__init__.py
limix_inference/lik/prod.py
limix_inference/lik/test/test_lik.py
limix_inference/link/__init__.py
limix_inference/link/link.py
limix_inference/link/test/test_link.py
limix_inference/lmm/__init__.py
limix_inference/lmm/core.py
limix_inference/lmm/lmm.py
limix_inference/lmm/scan.py
limix_inference/lmm/test/test_lmm.py
limix_inference/mean/__init__.py
limix_inference/mean/linear.py
limix_inference/mean/offset.py
limix_inference/mean/sum.py
limix_inference/mean/test/test_linear_mean.py
limix_inference/mean/test/test_offset_mean.py
limix_inference/mean/test/test_sum_mean.py
limix_inference/random/__init__.py
limix_inference/random/canonical.py
limix_inference/random/ggp.py
limix_inference/random/gp.py
limix_inference/random/test/test_sampling.py