Metadata-Version: 1.1
Name: limix-inference
Version: 1.1.6
Summary: Fast inference for Generalized Linear Mixed Models.
Home-page: https://github.com/limix/limix-inference
Author: Limix Developers
Author-email: horta@ebi.ac.uk
License: MIT
Platform: UNKNOWN
Classifier: Development Status :: 5 - Production/Stable
Classifier: License :: OSI Approved :: MIT License
Classifier: Operating System :: OS Independent
